pIceImarisConnector/.gitignore
pIceImarisConnector/__init__.py
pIceImarisConnector/pIceImarisConnector.py
pIceImarisConnector/test/.gitignore
pIceImarisConnector/test/__init__.py
pIceImarisConnector/test/HelloWorldXT.py
pIceImarisConnector/test/PyramidalCell.ims
pIceImarisConnector/test/SwimmingAlgae.ims
pIceImarisConnector/test/TestPIcePyramidalCellXT.py
pIceImarisConnector/test/TestPIceSwimmingAlgaeXT.py
pIceImarisConnector/test/TestStaticMethods.py
piceimarisconnector-0.4.3.dist-info/LICENSE.txt
piceimarisconnector-0.4.3.dist-info/METADATA
piceimarisconnector-0.4.3.dist-info/WHEEL
piceimarisconnector-0.4.3.dist-info/RECORD
