Metadata-Version: 2.1
Name: pIceImarisConnector
Version: 0.4.3
Summary: IceImarisConnector for python (pIceImarisConnector) is a simple commodity class that eases communication between Bitplane Imaris and python using the Imaris XT interface.
Home-page: https://github.com/aarpon/pIceImarisConnector
License: GPL-2.0-only
Keywords: Imaris,ImarisXT,python,Ice
Author: Aaron Ponti
Author-email: aaron.ponti@bsse.ethz.ch
Requires-Python: >=3.9,<3.12
Classifier: Development Status :: 5 - Production/Stable
Classifier: Intended Audience :: Developers
Classifier: License :: OSI Approved :: GNU General Public License v2 (GPLv2)
Classifier: Operating System :: Microsoft :: Windows
Classifier: Programming Language :: Python :: 3
Classifier: Programming Language :: Python :: 3.9
Classifier: Programming Language :: Python :: 3.10
Classifier: Programming Language :: Python :: 3.11
Classifier: Topic :: Scientific/Engineering
Requires-Dist: numpy (==1.26.4)
Project-URL: Bug Tracker, https://github.com/aarpon/pIceImarisConnector/issues
Project-URL: Documentation, https://piceimarisconnector.readthedocs.io
Project-URL: Repository, https://github.com/aarpon/pIceImarisConnector
